doubao_douyin_analysis_parse_mcp-1.0.1.dist-info/licenses/LICENSE
src/__init__.py
src/__main__.py
src/doubao_api.py
src/douyin_api.py
src/douyin_mcp_server.py
src/link_extractor.py
src/prompts.py
doubao_douyin_analysis_parse_mcp-1.0.1.dist-info/METADATA
doubao_douyin_analysis_parse_mcp-1.0.1.dist-info/WHEEL
doubao_douyin_analysis_parse_mcp-1.0.1.dist-info/entry_points.txt
doubao_douyin_analysis_parse_mcp-1.0.1.dist-info/top_level.txt
doubao_douyin_analysis_parse_mcp-1.0.1.dist-info/RECORD
