Metadata-Version: 2.4
Name: doubao-douyin-analysis-parse-mcp
Version: 1.0.1
Summary: MCP 服务器用于解析抖音视频链接并使用豆包模型进行视频内容分析
Author-email: youzhajun <shanxin2020@yeah.net>
License: MIT
Project-URL: Homepage, https://github.com/yourusername/douyin-mcp-server
Project-URL: Repository, https://github.com/yourusername/douyin-mcp-server
Project-URL: Issues, https://github.com/yourusername/douyin-mcp-server/issues
Project-URL: Documentation, https://github.com/yourusername/douyin-mcp-server#readme
Keywords: mcp,douyin,tiktok,video,ai,analysis,doubao,cursor
Classifier: Development Status :: 4 - Beta
Classifier: Intended Audience :: Developers
Classifier: License :: OSI Approved :: MIT License
Classifier: Programming Language :: Python :: 3
Classifier: Programming Language :: Python :: 3.10
Classifier: Programming Language :: Python :: 3.11
Classifier: Programming Language :: Python :: 3.12
Classifier: Topic :: Software Development :: Libraries :: Python Modules
Classifier: Topic :: Multimedia :: Video
Requires-Python: >=3.10
License-File: LICENSE
Requires-Dist: mcp>=1.0.0
Requires-Dist: httpx>=0.27.0
Requires-Dist: python-dotenv>=1.0.0
Provides-Extra: dev
Requires-Dist: pytest>=8.0.0; extra == "dev"
Requires-Dist: pytest-asyncio>=0.23.0; extra == "dev"
Dynamic: license-file
